<?xml version="1.0" encoding="UTF-8"?>
<!DOCTYPE properties SYSTEM "http://java.sun.com/dtd/properties.dtd">
<properties>
	<!-- switch to enable/disable app data service support -->
	<entry key="app-data-service-enabled">true</entry>

	<!-- switch to enable/disable currency data service support -->
	<entry key="currency-data-service-enabled">true</entry>

	<!-- switch to enable/disable login service support -->
	<entry key="login-service-enabled">true</entry>

	<!-- switch to enable/disable pricelayer data service support -->
	<entry key="pricelayer-data-service-enabled">true</entry>

	<!-- switch to enable/disable site data service support -->
	<entry key="site-data-service-enabled">true</entry>

	<!-- switch to enable/disable supplier data service support -->
	<entry key="supplier-data-service-enabled">true</entry>

    <entry key="adserving">true</entry>

    <entry key="banner-ad-data-service-enabled">true</entry>

	<entry key="video-ad-data-service-enabled">true</entry>

	<!-- handler class to use service App Data requests -->
	<entry key="app-data-handler-class">com.atg.openssp.dataprovider.provider.handler.AppDataHandler</entry>

	<!-- handler class to use service Curreny Data requests -->
	<entry key="currency-data-handler-class">com.atg.openssp.dataprovider.provider.handler.CurrencyDataHandler</entry>
	<entry key="currency-data-maintenance-handler-class">com.atg.openssp.dataprovider.provider.handler.CurrencyDataMaintenanceHandler</entry>

	<!-- handler class to use for service authorization grant requests -->
	<entry key="login-handler-class">com.atg.openssp.common.provider.LoginHandler</entry>

	<!-- handler class to use service Pricelayer Data requests -->
	<entry key="pricelayer-data-handler-class">com.atg.openssp.dataprovider.provider.handler.PricelayerDataHandler</entry>
	<entry key="pricelayer-data-maintenance-handler-class">com.atg.openssp.dataprovider.provider.handler.PricelayerDataMaintenanceHandler</entry>

	<!-- handler class to use service Site Data requests -->
	<entry key="site-data-handler-class">com.atg.openssp.dataprovider.provider.handler.SiteDataHandler</entry>
	<entry key="site-data-maintenance-handler-class">com.atg.openssp.dataprovider.provider.handler.SiteDataMaintenanceHandler</entry>

	<!-- handler class to use service Supplier Data requests -->
	<entry key="supplier-data-handler-class">com.atg.openssp.dataprovider.provider.handler.SupplierDataHandler</entry>
	<entry key="supplier-data-maintenance-handler-class">com.atg.openssp.dataprovider.provider.handler.SupplierDataMaintenanceHandler</entry>

	<entry key="banner-ad-data-handler-class">com.atg.openssp.dataprovider.provider.handler.BannerAdDataHandler</entry>
    <entry key="banner-ad-data-maintenance-handler-class">com.atg.openssp.dataprovider.provider.handler.BannerAdDataMaintenanceHandler</entry>
	<entry key="video-ad-data-handler-class">com.atg.openssp.dataprovider.provider.handler.VideoAdDataHandler</entry>
    <entry key="video-ad-data-maintenance-handler-class">com.atg.openssp.dataprovider.provider.handler.VideoAdDataMaintenanceHandler</entry>

	<entry key="geo-ip-info-handler-class">com.atg.openssp.common.core.exchange.geo.FreeGeoIpInfoHandler</entry>

	<!-- switch to enable/disable debugging -->
	<entry key="debug">true</entry>
	
	<!-- switch to enable/disable verbose output -->
	<entry key="verbose">false</entry>

</properties>
